setup.py
cratis_filer/__init__.py
cratis_filer/features.py
django_cratis_filer.egg-info/PKG-INFO
django_cratis_filer.egg-info/SOURCES.txt
django_cratis_filer.egg-info/dependency_links.txt
django_cratis_filer.egg-info/requires.txt
django_cratis_filer.egg-info/top_level.txt